dioritorm/__init__.py
dioritorm/core/Record.py
dioritorm/core/__init__.py
dioritorm/core/base.py
dioritorm/core/config_manager.py
dioritorm/core/constants.py
dioritorm/core/counter.py
dioritorm/core/data_field.py
dioritorm/core/document.py
dioritorm/core/entity.py
dioritorm/core/event.py
dioritorm/core/inforecord.py
dioritorm/core/object.py
dioritorm/core/reference.py
dioritorm/core/registry.py
dioritorm/core/table_section.py
dioritorm/core/table_section_record.py
dioritorm/core/tables.py
dioritorm/core/Database/Filter.py
dioritorm/core/Database/OrderBy.py
dioritorm/core/Database/__init__.py
dioritorm/core/Database/databasehandler.py
dioritorm/core/Database/databasemanager.py
dioritorm/core/Database/mysqlhandler.py
dioritorm/core/Database/sqllitehandler.py
dioritorm/core/Fields/__init__.py
dioritorm/core/Fields/boolean.py
dioritorm/core/Fields/datetime.py
dioritorm/core/Fields/number.py
dioritorm/core/Fields/string.py
dioritorm/core/Sync/__init__.py
dioritorm/core/Sync/apimessage.py
dioritorm/core/Sync/sync_handler.py
diorit_orm-0.2.1.dist-info/METADATA
diorit_orm-0.2.1.dist-info/WHEEL
diorit_orm-0.2.1.dist-info/top_level.txt
diorit_orm-0.2.1.dist-info/RECORD
