Metadata-Version: 2.4
Name: diorit.orm
Version: 0.2.1
Summary: Data-modeling core for application development
Author: bogdanAntonjuk
Author-email: info@diorit.com.ua
Classifier: Programming Language :: Python :: 3
Classifier: License :: OSI Approved :: MIT License
Classifier: Operating System :: OS Independent
Requires-Dist: mysql-connector-python
Dynamic: author
Dynamic: author-email
Dynamic: classifier
Dynamic: requires-dist
Dynamic: summary
